CHANGES.txt
LICENSE.txt
MANIFEST.in
README.txt
setup.py
js/__init__.py
js.jquery_utils.egg-info/PKG-INFO
js.jquery_utils.egg-info/SOURCES.txt
js.jquery_utils.egg-info/dependency_links.txt
js.jquery_utils.egg-info/entry_points.txt
js.jquery_utils.egg-info/namespace_packages.txt
js.jquery_utils.egg-info/not-zip-safe
js.jquery_utils.egg-info/requires.txt
js.jquery_utils.egg-info/top_level.txt
js/jquery_utils/__init__.py
js/jquery_utils/test_jquery_utils.txt
js/jquery_utils/resources/README.txt
js/jquery_utils/resources/jquery.ddbelated.js
js/jquery_utils/resources/jquery.ddbelated.min.js
js/jquery_utils/resources/jquery.utils.css
js/jquery_utils/resources/jquery.utils.js
js/jquery_utils/resources/jquery.utils.lite.js
js/jquery_utils/resources/jquery.utils.lite.min.js
js/jquery_utils/resources/jquery.utils.min.js