Metadata-Version: 1.0
Name: js.jquery-utils
Version: 0.8.5
Summary: Fanstatic packaging of jQuery Utils
Home-page: UNKNOWN
Author: Fanstatic Developers
Author-email: fanstatic@googlegroups.com
License: BSD
Platform: UNKNOWN
